mcpid/__init__.py
mcpid/_mcpid.csv
mcpid/_version.py
mcpid/lookup.py
mcpid-0.0.4.dist-info/LICENSE-DATA.txt
mcpid-0.0.4.dist-info/LICENSE.txt
mcpid-0.0.4.dist-info/METADATA
mcpid-0.0.4.dist-info/WHEEL
mcpid-0.0.4.dist-info/top_level.txt
mcpid-0.0.4.dist-info/RECORD
