Metadata-Version: 2.1
Name: mcpid
Version: 0.0.4
Summary: Numpy interface to MCPID / PDG data.
Home-page: https://github.com/jacanchaplais/mcpid
Author: Jacan Chaplais
Author-email: jacanchaplais@gmail.com
License: BSD 3-Clause License
Classifier: Programming Language :: Python :: 3
Classifier: License :: OSI Approved :: BSD License
Classifier: Operating System :: OS Independent
License-File: LICENSE-DATA.txt
License-File: LICENSE.txt
Requires-Dist: numpy
Requires-Dist: pandas
